tkwinico/__init__.py
tkwinico/__main__.py
tkwinico/const.py
tkwinico/demo.tcl
tkwinico/load.py
tkwinico/manpage.css
tkwinico/pkgIndex.tcl
tkwinico/sample.tcl
tkwinico/sample2.tcl
tkwinico/smiley.ico
tkwinico/test.py
tkwinico/tkchat.ico
tkwinico/winico.html
tkwinico/winico.py
tkwinico/Winico0.7.1.dll
tkwinico-1.5.71.dist-info/METADATA
tkwinico-1.5.71.dist-info/WHEEL
tkwinico-1.5.71.dist-info/RECORD
