Metadata-Version: 2.1
Name: tkwinico
Version: 1.5.71
Summary: Tray Icon for Windows
Author: XiangQinxi
Author-email: XiangQinxi@outlook.com
Requires-Python: >=3.8,<4.0
Classifier: Programming Language :: Python :: 3
Classifier: Programming Language :: Python :: 3.8
Classifier: Programming Language :: Python :: 3.9
Classifier: Programming Language :: Python :: 3.10
Classifier: Programming Language :: Python :: 3.11
Project-URL: Documentation, https://tkdev-docs.netlify.app/api/devtcl/winico/officialdocs/
